[
  {
    "incidentId": "121983920",
    "incidentType": "QI",
    "FACJobStatusCode": "A",
    "OANNumber": "1018694",
    "outageStartDateTime": "10/31/2019 11:22:00 AM",
    "versionDate": "10/31/2019 7:40:09 PM",
    "lastChangeDateTime": "10/31/2019 7:36:02 PM",
    "estimateCLUDateTime": "Not Available",
    "memoCauseCode": "15",
    "memoCauseCodeDescription": "Analyzing Problem",
    "crewStatusCode": "01",
    "crewStatusCodeDescription": "We are aware of the problem.",
    "resultCode": "0",
    "resultCodeDesription": "Not Available",
    "numberOfCustomersAffected": "46",
    "zipCode": "93066",
    "countyName": "Ventura                                 ",
    "cityName": "Unincorporated Area - Ventura County",
    "districtNumber": "39",
    "sectorNumber": "SANTA CLARA",
    "ERTCode": "2",
    "centroidX": "-119.106572897881",
    "centroidY": "34.27641554281960"
  },
  {
    "incidentId": "121978890",
    "incidentType": "Not Available",
    "FACJobStatusCode": "F",
    "OANNumber": "1018396",
    "outageStartDateTime": "10/30/2019 5:24:52 AM",
    "versionDate": "10/31/2019 7:40:09 PM",
    "lastChangeDateTime": "10/31/2019 7:02:18 PM",
    "estimateCLUDateTime": "Not Available",
    "memoCauseCode": "15",
    "memoCauseCodeDescription": "Analyzing Problem",
    "crewStatusCode": "02",
    "crewStatusCodeDescription": "We have notified our repair crews. ",
    "resultCode": "0",
    "resultCodeDesription": "Not Available",
    "numberOfCustomersAffected": "2",
    "zipCode": "93063",
    "countyName": "Ventura                                 ",
    "cityName": "Simi Valley",
    "districtNumber": "35",
    "sectorNumber": "MOORPARK",
    "ERTCode": "02",
    "centroidX": "-118.713419257559",
    "centroidY": "34.298912502933"
  },
  {
    "incidentId": "121932157",
    "incidentType": "PO",
    "FACJobStatusCode": "W",
    "OANNumber": "1015236",
    "outageStartDateTime": "10/31/2019 8:45:00 AM",
    "versionDate": "10/31/2019 7:40:09 PM",
    "lastChangeDateTime": "10/31/2019 2:06:27 PM",
    "estimateCLUDateTime": "Currently Being Re-evaluated",
    "memoCauseCode": "22",
    "memoCauseCodeDescription": "Transformer Upgrade",
    "crewStatusCode": "04",
    "crewStatusCodeDescription": "Work is in progress.",
    "resultCode": "01",
    "resultCodeDesription": "Enhancing Reliability",
    "numberOfCustomersAffected": "35",
    "zipCode": "91709",
    "countyName": "San Bernardino                          ",
    "cityName": "Chino Hills",
    "districtNumber": "34",
    "sectorNumber": "MIRALOMA",
    "ERTCode": "07",
    "centroidX": "-117.698553996258",
    "centroidY": "33.96562300104340"
  },
  {
    "incidentId": "121981469",
    "incidentType": "Not Available",
    "FACJobStatusCode": "D",
    "OANNumber": "1018526",
    "outageStartDateTime": "10/31/2019 5:20:36 AM",
    "versionDate": "10/31/2019 7:40:09 PM",
    "lastChangeDateTime": "10/31/2019 5:37:35 PM",
    "estimateCLUDateTime": "Most up by 11/1/2019 3:00:00 PM",
    "memoCauseCode": "11",
    "memoCauseCodeDescription": "Traffic Accident",
    "crewStatusCode": "11",
    "crewStatusCodeDescription": "We have identified the problem and are working to restore your service.",
    "resultCode": "06",
    "resultCodeDesription": "Equipment Damage",
    "numberOfCustomersAffected": "19",
    "zipCode": "92509",
    "countyName": "Riverside                               ",
    "cityName": "Jurupa Valley",
    "districtNumber": "30",
    "sectorNumber": "VISTA",
    "ERTCode": "05",
    "centroidX": "-117.423389370657",
    "centroidY": "33.98001398393330"
  },
  {
    "incidentId": "121983424",
    "incidentType": "Not Available",
    "FACJobStatusCode": "D",
    "OANNumber": "1018628",
    "outageStartDateTime": "10/31/2019 10:44:26 AM",
    "versionDate": "10/31/2019 7:40:09 PM",
    "lastChangeDateTime": "10/31/2019 11:46:00 AM",
    "estimateCLUDateTime": "Not Available",
    "memoCauseCode": "15",
    "memoCauseCodeDescription": "Analyzing Problem",
    "crewStatusCode": "02",
    "crewStatusCodeDescription": "We have notified our repair crews. ",
    "resultCode": "0",
    "resultCodeDesription": "Not Available",
    "numberOfCustomersAffected": "4",
    "zipCode": "91302",
    "countyName": "Los Angeles                             ",
    "cityName": "Unincorporated Area - Los Angeles County",
    "districtNumber": "35",
    "sectorNumber": "MOORPARK",
    "ERTCode": "2",
    "centroidX": "-118.680112557457",
    "centroidY": "34.15182038691570"
  },
  {
    "incidentId": "121982828",
    "incidentType": "Not Available",
    "FACJobStatusCode": "D",
    "OANNumber": "1018758",
    "outageStartDateTime": "10/31/2019 8:53:06 AM",
    "versionDate": "10/31/2019 7:40:09 PM",
    "lastChangeDateTime": "10/31/2019 6:40:20 PM",
    "estimateCLUDateTime": "10/31/2019 11:00:00 PM",
    "memoCauseCode": "16",
    "memoCauseCodeDescription": "Equipment Problems",
    "crewStatusCode": "04",
    "crewStatusCodeDescription": "Work is in progress.",
    "resultCode": "0",
    "resultCodeDesription": "Not Available",
    "numberOfCustomersAffected": "15",
    "zipCode": "92571",
    "countyName": "Riverside                               ",
    "cityName": "Perris",
    "districtNumber": "77",
    "sectorNumber": "VALLEY",
    "ERTCode": "06",
    "centroidX": "-117.225691",
    "centroidY": "33.80678000000620"
  },
  {
    "incidentId": "121982410",
    "incidentType": "Not Available",
    "FACJobStatusCode": "D",
    "OANNumber": "1018532",
    "outageStartDateTime": "10/31/2019 7:09:29 AM",
    "versionDate": "10/31/2019 7:40:09 PM",
    "lastChangeDateTime": "10/31/2019 2:08:22 PM",
    "estimateCLUDateTime": "10/31/2019 9:00:00 PM",
    "memoCauseCode": "16",
    "memoCauseCodeDescription": "Equipment Problems",
    "crewStatusCode": "04",
    "crewStatusCodeDescription": "Work is in progress.",
    "resultCode": "0",
    "resultCodeDesription": "Not Available",
    "numberOfCustomersAffected": "56",
    "zipCode": "92270",
    "countyName": "Riverside                               ",
    "cityName": "Rancho Mirage",
    "districtNumber": "79",
    "sectorNumber": "DEVERS",
    "ERTCode": "07",
    "centroidX": "-116.438413166426",
    "centroidY": "33.77356683345020"
  },
  {
    "incidentId": "121940457",
    "incidentType": "PO",
    "FACJobStatusCode": "D",
    "OANNumber": "1015825",
    "outageStartDateTime": "10/31/2019 4:58:13 PM",
    "versionDate": "10/31/2019 7:40:09 PM",
    "lastChangeDateTime": "10/31/2019 7:34:24 PM",
    "estimateCLUDateTime": "Currently Being Re-evaluated",
    "memoCauseCode": "07",
    "memoCauseCodeDescription": "Upgrading Equipment",
    "crewStatusCode": "04",
    "crewStatusCodeDescription": "Work is in progress.",
    "resultCode": "01",
    "resultCodeDesription": "Enhancing Reliability",
    "numberOfCustomersAffected": "4",
    "zipCode": "93560",
    "countyName": "Kern                                    ",
    "cityName": "Rosamond",
    "districtNumber": "36",
    "sectorNumber": "VINCENT",
    "ERTCode": "07",
    "centroidX": "-118.292044334469",
    "centroidY": "34.89959967213520"
  },
  {
    "incidentId": "121980277",
    "incidentType": "Not Available",
    "FACJobStatusCode": "F",
    "OANNumber": "1018465",
    "outageStartDateTime": "10/30/2019 8:26:08 PM",
    "versionDate": "10/31/2019 7:40:09 PM",
    "lastChangeDateTime": "10/31/2019 10:04:13 AM",
    "estimateCLUDateTime": "10/31/2019 10:00:00 PM",
    "memoCauseCode": "08",
    "memoCauseCodeDescription": "Fire",
    "crewStatusCode": "04",
    "crewStatusCodeDescription": "Work is in progress.",
    "resultCode": "02",
    "resultCodeDesription": "Power Poles and Lines Down",
    "numberOfCustomersAffected": "24",
    "zipCode": "90002",
    "countyName": "Los Angeles                             ",
    "cityName": "Florence-Graham",
    "districtNumber": "32",
    "sectorNumber": "LIGHTHIPE",
    "ERTCode": "07",
    "centroidX": "-118.231719736892",
    "centroidY": "33.95023320364570"
  },
  {
    "incidentId": "121974125",
    "incidentType": "Not Available",
    "FACJobStatusCode": "F",
    "OANNumber": "1018176",
    "outageStartDateTime": "10/30/2019 6:25:27 AM",
    "versionDate": "10/31/2019 7:40:09 PM",
    "lastChangeDateTime": "10/31/2019 2:00:43 PM",
    "estimateCLUDateTime": "Not Available",
    "memoCauseCode": "16",
    "memoCauseCodeDescription": "Equipment Problems",
    "crewStatusCode": "04",
    "crewStatusCodeDescription": "Work is in progress.",
    "resultCode": "0",
    "resultCodeDesription": "Not Available",
    "numberOfCustomersAffected": "4",
    "zipCode": "90265",
    "countyName": "Los Angeles                             ",
    "cityName": "Unincorporated Area - Los Angeles County",
    "districtNumber": "35",
    "sectorNumber": "MOORPARK",
    "ERTCode": "02",
    "centroidX": "-118.742964",
    "centroidY": "34.06105150000780"
  },
  {
    "incidentId": "121942192",
    "incidentType": "PO",
    "FACJobStatusCode": "D",
    "OANNumber": "1015967",
    "outageStartDateTime": "10/31/2019 8:00:00 AM",
    "versionDate": "10/31/2019 7:40:09 PM",
    "lastChangeDateTime": "10/31/2019 7:18:52 PM",
    "estimateCLUDateTime": "10/31/2019 10:00:00 PM",
    "memoCauseCode": "21",
    "memoCauseCodeDescription": "Pole Upgrade",
    "crewStatusCode": "04",
    "crewStatusCodeDescription": "Work is in progress.",
    "resultCode": "01",
    "resultCodeDesription": "Enhancing Reliability",
    "numberOfCustomersAffected": "152",
    "zipCode": "No Zip Code",
    "countyName": "San Bernardino                          ",
    "cityName": "Crestline",
    "districtNumber": "40",
    "sectorNumber": "ARROWHEAD",
    "ERTCode": "07",
    "centroidX": "-117.280139191172",
    "centroidY": "34.24970047382570"
  },
  {
    "incidentId": "121973829",
    "incidentType": "Not Available",
    "FACJobStatusCode": "D",
    "OANNumber": "1018098",
    "outageStartDateTime": "10/30/2019 6:22:46 AM",
    "versionDate": "10/31/2019 7:40:09 PM",
    "lastChangeDateTime": "10/31/2019 3:49:43 PM",
    "estimateCLUDateTime": "Not Available",
    "memoCauseCode": "08",
    "memoCauseCodeDescription": "Fire",
    "crewStatusCode": "04",
    "crewStatusCodeDescription": "Work is in progress.",
    "resultCode": "06",
    "resultCodeDesription": "Equipment Damage",
    "numberOfCustomersAffected": "264",
    "zipCode": "93021",
    "countyName": "Ventura                                 ",
    "cityName": "Moorpark",
    "districtNumber": "35",
    "sectorNumber": "MOORPARK",
    "ERTCode": "02",
    "centroidX": "-118.831184998612",
    "centroidY": "34.28916157551970"
  },
  {
    "incidentId": "121980278",
    "incidentType": "Not Available",
    "FACJobStatusCode": "F",
    "OANNumber": "1018466",
    "outageStartDateTime": "10/30/2019 8:26:08 PM",
    "versionDate": "10/31/2019 7:40:09 PM",
    "lastChangeDateTime": "10/31/2019 10:06:41 AM",
    "estimateCLUDateTime": "10/31/2019 10:00:00 PM",
    "memoCauseCode": "08",
    "memoCauseCodeDescription": "Fire",
    "crewStatusCode": "04",
    "crewStatusCodeDescription": "Work is in progress.",
    "resultCode": "02",
    "resultCodeDesription": "Power Poles and Lines Down",
    "numberOfCustomersAffected": "8",
    "zipCode": "90002",
    "countyName": "Los Angeles                             ",
    "cityName": "Florence-Graham",
    "districtNumber": "32",
    "sectorNumber": "LIGHTHIPE",
    "ERTCode": "07",
    "centroidX": "-118.231532440432",
    "centroidY": "33.94975421213590"
  },
  {
    "incidentId": "121980965",
    "incidentType": "Not Available",
    "FACJobStatusCode": "D",
    "OANNumber": "1018504",
    "outageStartDateTime": "10/31/2019 1:18:55 AM",
    "versionDate": "10/31/2019 7:40:09 PM",
    "lastChangeDateTime": "10/31/2019 1:21:13 PM",
    "estimateCLUDateTime": "Not Available",
    "memoCauseCode": "15",
    "memoCauseCodeDescription": "Analyzing Problem",
    "crewStatusCode": "02",
    "crewStatusCodeDescription": "We have notified our repair crews. ",
    "resultCode": "0",
    "resultCodeDesription": "Not Available",
    "numberOfCustomersAffected": "90",
    "zipCode": "90265",
    "countyName": "Los Angeles                             ",
    "cityName": "Malibu",
    "districtNumber": "35",
    "sectorNumber": "MOORPARK",
    "ERTCode": "2",
    "centroidX": "-118.683887219268",
    "centroidY": "34.04357116202320"
  },
  {
    "incidentId": "121981136",
    "incidentType": "Not Available",
    "FACJobStatusCode": "F",
    "OANNumber": "1018514",
    "outageStartDateTime": "10/31/2019 2:29:15 AM",
    "versionDate": "10/31/2019 7:40:09 PM",
    "lastChangeDateTime": "10/31/2019 5:38:02 PM",
    "estimateCLUDateTime": "Most up by 11/1/2019 3:00:00 PM",
    "memoCauseCode": "11",
    "memoCauseCodeDescription": "Traffic Accident",
    "crewStatusCode": "11",
    "crewStatusCodeDescription": "We have identified the problem and are working to restore your service.",
    "resultCode": "06",
    "resultCodeDesription": "Equipment Damage",
    "numberOfCustomersAffected": "8",
    "zipCode": "92509",
    "countyName": "Riverside                               ",
    "cityName": "Jurupa Valley",
    "districtNumber": "30",
    "sectorNumber": "VISTA",
    "ERTCode": "05",
    "centroidX": "-117.420393992254",
    "centroidY": "33.983340804963"
  },
  {
    "incidentId": "121926848",
    "incidentType": "PO",
    "FACJobStatusCode": "D",
    "OANNumber": "1014792",
    "outageStartDateTime": "10/29/2019 8:00:00 AM",
    "versionDate": "10/31/2019 7:40:09 PM",
    "lastChangeDateTime": "10/31/2019 4:35:19 PM",
    "estimateCLUDateTime": "Currently Being Re-evaluated",
    "memoCauseCode": "07",
    "memoCauseCodeDescription": "Upgrading Equipment",
    "crewStatusCode": "04",
    "crewStatusCodeDescription": "Work is in progress.",
    "resultCode": "01",
    "resultCodeDesription": "Enhancing Reliability",
    "numberOfCustomersAffected": "2",
    "zipCode": "92397",
    "countyName": "San Bernardino                          ",
    "cityName": "Wrightwood",
    "districtNumber": "73",
    "sectorNumber": "LUGO",
    "ERTCode": "07",
    "centroidX": "-117.635712089776",
    "centroidY": "34.36497320466110"
  },
  {
    "incidentId": "121981402",
    "incidentType": "Not Available",
    "FACJobStatusCode": "F",
    "OANNumber": "1018518",
    "outageStartDateTime": "10/31/2019 3:42:31 AM",
    "versionDate": "10/31/2019 7:40:09 PM",
    "lastChangeDateTime": "10/31/2019 6:38:40 PM",
    "estimateCLUDateTime": "Not Available",
    "memoCauseCode": "15",
    "memoCauseCodeDescription": "Analyzing Problem",
    "crewStatusCode": "02",
    "crewStatusCodeDescription": "We have notified our repair crews. ",
    "resultCode": "0",
    "resultCodeDesription": "Not Available",
    "numberOfCustomersAffected": "451",
    "zipCode": "92407",
    "countyName": "San Bernardino                          ",
    "cityName": "San Bernardino",
    "districtNumber": "31",
    "sectorNumber": "VISTA",
    "ERTCode": "02",
    "centroidX": "-117.284645642160",
    "centroidY": "34.17762411964120"
  },
  {
    "incidentId": "121983539",
    "incidentType": "Not Available",
    "FACJobStatusCode": "F",
    "OANNumber": "1018643",
    "outageStartDateTime": "10/31/2019 11:07:44 AM",
    "versionDate": "10/31/2019 7:40:09 PM",
    "lastChangeDateTime": "10/31/2019 6:04:00 PM",
    "estimateCLUDateTime": "11/1/2019 2:00:00 AM",
    "memoCauseCode": "14",
    "memoCauseCodeDescription": "Storm Conditions",
    "crewStatusCode": "11",
    "crewStatusCodeDescription": "We have identified the problem and are working to restore your service.",
    "resultCode": "05",
    "resultCodeDesription": "Damage Underground Service",
    "numberOfCustomersAffected": "35",
    "zipCode": "92337",
    "countyName": "San Bernardino                          ",
    "cityName": "Fontana",
    "districtNumber": "30",
    "sectorNumber": "VISTA",
    "ERTCode": "07",
    "centroidX": "-117.431316625069",
    "centroidY": "34.06345812934640"
  },
  {
    "incidentId": "121984155",
    "incidentType": "Not Available",
    "FACJobStatusCode": "F",
    "OANNumber": "1018719",
    "outageStartDateTime": "10/31/2019 1:38:08 PM",
    "versionDate": "10/31/2019 7:40:09 PM",
    "lastChangeDateTime": "10/31/2019 5:34:11 PM",
    "estimateCLUDateTime": "11/1/2019 7:00:00 AM",
    "memoCauseCode": "11",
    "memoCauseCodeDescription": "Traffic Accident",
    "crewStatusCode": "04",
    "crewStatusCodeDescription": "Work is in progress.",
    "resultCode": "02",
    "resultCodeDesription": "Power Poles and Lines Down",
    "numberOfCustomersAffected": "135",
    "zipCode": "91803",
    "countyName": "Los Angeles                             ",
    "cityName": "Alhambra",
    "districtNumber": "22",
    "sectorNumber": "MESA",
    "ERTCode": "06",
    "centroidX": "-118.146027330936",
    "centroidY": "34.07419292087980"
  },
  {
    "incidentId": "121985105",
    "incidentType": "Not Available",
    "FACJobStatusCode": "F",
    "OANNumber": "1018777",
    "outageStartDateTime": "10/31/2019 7:17:06 PM",
    "versionDate": "10/31/2019 7:40:09 PM",
    "lastChangeDateTime": "10/31/2019 7:37:28 PM",
    "estimateCLUDateTime": "Most up by 10/31/2019 8:17:06 PM",
    "memoCauseCode": "15",
    "memoCauseCodeDescription": "Analyzing Problem",
    "crewStatusCode": "02",
    "crewStatusCodeDescription": "We have notified our repair crews. ",
    "resultCode": "0",
    "resultCodeDesription": "Not Available",
    "numberOfCustomersAffected": "11",
    "zipCode": "92407",
    "countyName": "San Bernardino                          ",
    "cityName": "Unincorporated Area - San Bernardino County",
    "districtNumber": "31",
    "sectorNumber": "VISTA",
    "ERTCode": "01",
    "centroidX": "-117.328475610583",
    "centroidY": "34.20110251636840"
  },
  {
    "incidentId": "121985119",
    "incidentType": "Not Available",
    "FACJobStatusCode": "A",
    "OANNumber": "1018778",
    "outageStartDateTime": "10/31/2019 7:25:50 PM",
    "versionDate": "10/31/2019 7:40:09 PM",
    "lastChangeDateTime": "10/31/2019 7:33:44 PM",
    "estimateCLUDateTime": "Most up by 10/31/2019 8:25:50 PM",
    "memoCauseCode": "15",
    "memoCauseCodeDescription": "Analyzing Problem",
    "crewStatusCode": "02",
    "crewStatusCodeDescription": "We have notified our repair crews. ",
    "resultCode": "0",
    "resultCodeDesription": "Not Available",
    "numberOfCustomersAffected": "42",
    "zipCode": "93066",
    "countyName": "Ventura                                 ",
    "cityName": "Unincorporated Area - Ventura County",
    "districtNumber": "39",
    "sectorNumber": "SANTA CLARA",
    "ERTCode": "01",
    "centroidX": "-119.054471781137",
    "centroidY": "34.33979966537150"
  },
  {
    "incidentId": "121984930",
    "incidentType": "Not Available",
    "FACJobStatusCode": "A",
    "OANNumber": "1018774",
    "outageStartDateTime": "10/31/2019 5:20:20 PM",
    "versionDate": "10/31/2019 7:40:09 PM",
    "lastChangeDateTime": "10/31/2019 7:20:57 PM",
    "estimateCLUDateTime": "Most up by 11/1/2019 2:30:00 AM",
    "memoCauseCode": "15",
    "memoCauseCodeDescription": "Analyzing Problem",
    "crewStatusCode": "01",
    "crewStatusCodeDescription": "We are aware of the problem.",
    "resultCode": "0",
    "resultCodeDesription": "Not Available",
    "numberOfCustomersAffected": "15",
    "zipCode": "91766",
    "countyName": "Los Angeles                             ",
    "cityName": "Pomona",
    "districtNumber": "26",
    "sectorNumber": "MIRALOMA",
    "ERTCode": "05",
    "centroidX": "-117.73378150",
    "centroidY": "34.02945200000350"
  }
]