[
  {
    "incidentId": "121761223",
    "incidentType": "PO",
    "FACJobStatusCode": "D",
    "OANNumber": "1001201",
    "outageStartDateTime": "9/10/2019 8:30:00 AM",
    "versionDate": "9/10/2019 5:40:18 PM",
    "lastChangeDateTime": "9/10/2019 5:36:05 PM",
    "estimateCLUDateTime": "Currently Being Re-evaluated",
    "memoCauseCode": "21",
    "memoCauseCodeDescription": "Pole Upgrade",
    "crewStatusCode": "04",
    "crewStatusCodeDescription": "Work is in progress.",
    "resultCode": "01",
    "resultCodeDesription": "Enhancing Reliability",
    "numberOfCustomersAffected": "1",
    "zipCode": "00026",
    "countyName": "Tulare                                  ",
    "cityName": "Unincorporated Area - Tulare County",
    "districtNumber": "51",
    "sectorNumber": "SAN JOAQUIN",
    "ERTCode": "06",
    "centroidX": "-118.91877350",
    "centroidY": "36.268899000015"
  },
  {
    "incidentId": "121762246",
    "incidentType": "PO",
    "FACJobStatusCode": "D",
    "OANNumber": "1001405",
    "outageStartDateTime": "9/10/2019 2:00:41 PM",
    "versionDate": "9/10/2019 5:40:18 PM",
    "lastChangeDateTime": "9/10/2019 2:53:15 PM",
    "estimateCLUDateTime": "9/10/2019 8:00:00 PM",
    "memoCauseCode": "21",
    "memoCauseCodeDescription": "Pole Upgrade",
    "crewStatusCode": "04",
    "crewStatusCodeDescription": "Work is in progress.",
    "resultCode": "01",
    "resultCodeDesription": "Enhancing Reliability",
    "numberOfCustomersAffected": "1",
    "zipCode": "91384",
    "countyName": "Los Angeles                             ",
    "cityName": "Unincorporated Area - Los Angeles County",
    "districtNumber": "59",
    "sectorNumber": "SAUGUS",
    "ERTCode": "06",
    "centroidX": "-118.667013",
    "centroidY": "34.41512500000370"
  },
  {
    "incidentId": "121762694",
    "incidentType": "PO",
    "FACJobStatusCode": "D",
    "OANNumber": "1001493",
    "outageStartDateTime": "9/10/2019 8:00:44 AM",
    "versionDate": "9/10/2019 5:40:18 PM",
    "lastChangeDateTime": "9/10/2019 4:21:03 PM",
    "estimateCLUDateTime": "9/10/2019 7:00:00 PM",
    "memoCauseCode": "07",
    "memoCauseCodeDescription": "Upgrading Equipment",
    "crewStatusCode": "04",
    "crewStatusCodeDescription": "Work is in progress.",
    "resultCode": "01",
    "resultCodeDesription": "Enhancing Reliability",
    "numberOfCustomersAffected": "2",
    "zipCode": "93015",
    "countyName": "Ventura                                 ",
    "cityName": "Unincorporated Area - Ventura County",
    "districtNumber": "39",
    "sectorNumber": "SANTA CLARA",
    "ERTCode": "07",
    "centroidX": "-118.863433838334",
    "centroidY": "34.39774800418920"
  },
  {
    "incidentId": "121808569",
    "incidentType": "Not Available",
    "FACJobStatusCode": "W",
    "OANNumber": "1005101",
    "outageStartDateTime": "9/10/2019 3:52:09 PM",
    "versionDate": "9/10/2019 5:40:18 PM",
    "lastChangeDateTime": "9/10/2019 5:31:35 PM",
    "estimateCLUDateTime": "Most up by 9/10/2019 10:30:00 PM",
    "memoCauseCode": "15",
    "memoCauseCodeDescription": "Analyzing Problem",
    "crewStatusCode": "06",
    "crewStatusCodeDescription": "We are looking into the cause of the problem.",
    "resultCode": "0",
    "resultCodeDesription": "Not Available",
    "numberOfCustomersAffected": "9",
    "zipCode": "92708",
    "countyName": "Orange                                  ",
    "cityName": "Fountain Valley",
    "districtNumber": "33",
    "sectorNumber": "ELLIS",
    "ERTCode": "05",
    "centroidX": "-117.935565",
    "centroidY": "33.701493000010"
  },
  {
    "incidentId": "121767697",
    "incidentType": "PO",
    "FACJobStatusCode": "D",
    "OANNumber": "1002126",
    "outageStartDateTime": "9/10/2019 8:01:12 AM",
    "versionDate": "9/10/2019 5:40:18 PM",
    "lastChangeDateTime": "9/10/2019 1:40:14 PM",
    "estimateCLUDateTime": "Currently Being Re-evaluated",
    "memoCauseCode": "07",
    "memoCauseCodeDescription": "Upgrading Equipment",
    "crewStatusCode": "04",
    "crewStatusCodeDescription": "Work is in progress.",
    "resultCode": "01",
    "resultCodeDesription": "Enhancing Reliability",
    "numberOfCustomersAffected": "9",
    "zipCode": "93023",
    "countyName": "Ventura                                 ",
    "cityName": "Unincorporated Area - Ventura County",
    "districtNumber": "39",
    "sectorNumber": "SANTA CLARA",
    "ERTCode": "06",
    "centroidX": "-119.258939023788",
    "centroidY": "34.42498075686530"
  },
  {
    "incidentId": "121762454",
    "incidentType": "PO",
    "FACJobStatusCode": "D",
    "OANNumber": "1001444",
    "outageStartDateTime": "9/10/2019 1:15:01 PM",
    "versionDate": "9/10/2019 5:40:18 PM",
    "lastChangeDateTime": "9/10/2019 1:42:56 PM",
    "estimateCLUDateTime": "Currently Being Re-evaluated",
    "memoCauseCode": "21",
    "memoCauseCodeDescription": "Pole Upgrade",
    "crewStatusCode": "04",
    "crewStatusCodeDescription": "Work is in progress.",
    "resultCode": "01",
    "resultCodeDesription": "Enhancing Reliability",
    "numberOfCustomersAffected": "33",
    "zipCode": "93561",
    "countyName": "Kern                                    ",
    "cityName": "Tehachapi",
    "districtNumber": "52",
    "sectorNumber": "TEHACHAPI",
    "ERTCode": "06",
    "centroidX": "-118.452102332468",
    "centroidY": "35.12623966679570"
  },
  {
    "incidentId": "121807931",
    "incidentType": "Not Available",
    "FACJobStatusCode": "F",
    "OANNumber": "1004986",
    "outageStartDateTime": "9/10/2019 11:54:24 AM",
    "versionDate": "9/10/2019 5:40:18 PM",
    "lastChangeDateTime": "9/10/2019 4:48:59 PM",
    "estimateCLUDateTime": "9/11/2019 1:00:00 AM",
    "memoCauseCode": "09",
    "memoCauseCodeDescription": "Extreme Heat",
    "crewStatusCode": "04",
    "crewStatusCodeDescription": "Work is in progress.",
    "resultCode": "06",
    "resultCodeDesription": "Equipment Damage",
    "numberOfCustomersAffected": "10",
    "zipCode": "91706",
    "countyName": "Los Angeles                             ",
    "cityName": "Baldwin Park",
    "districtNumber": "27",
    "sectorNumber": "MESA",
    "ERTCode": "07",
    "centroidX": "-117.952835249720",
    "centroidY": "34.08800900071510"
  },
  {
    "incidentId": "121807935",
    "incidentType": "Not Available",
    "FACJobStatusCode": "W",
    "OANNumber": "1004990",
    "outageStartDateTime": "9/10/2019 11:53:52 AM",
    "versionDate": "9/10/2019 5:40:18 PM",
    "lastChangeDateTime": "9/10/2019 2:28:50 PM",
    "estimateCLUDateTime": "Currently Being Re-evaluated",
    "memoCauseCode": "16",
    "memoCauseCodeDescription": "Equipment Problems",
    "crewStatusCode": "04",
    "crewStatusCodeDescription": "Work is in progress.",
    "resultCode": "0",
    "resultCodeDesription": "Not Available",
    "numberOfCustomersAffected": "29",
    "zipCode": "90405",
    "countyName": "Los Angeles                             ",
    "cityName": "Santa Monica",
    "districtNumber": "42",
    "sectorNumber": "EL NIDO",
    "ERTCode": "06",
    "centroidX": "-118.472628",
    "centroidY": "34.00614600000370"
  },
  {
    "incidentId": "121808024",
    "incidentType": "Not Available",
    "FACJobStatusCode": "W",
    "OANNumber": "1005003",
    "outageStartDateTime": "9/10/2019 12:27:00 PM",
    "versionDate": "9/10/2019 5:40:18 PM",
    "lastChangeDateTime": "9/10/2019 12:32:14 PM",
    "estimateCLUDateTime": "9/10/2019 7:00:00 PM",
    "memoCauseCode": "16",
    "memoCauseCodeDescription": "Equipment Problems",
    "crewStatusCode": "04",
    "crewStatusCodeDescription": "Work is in progress.",
    "resultCode": "0",
    "resultCodeDesription": "Not Available",
    "numberOfCustomersAffected": "40",
    "zipCode": "90220",
    "countyName": "Los Angeles                             ",
    "cityName": "Unincorporated Area - Los Angeles County",
    "districtNumber": "32",
    "sectorNumber": "LIGHTHIPE",
    "ERTCode": "06",
    "centroidX": "-118.225884",
    "centroidY": "33.85490900000620"
  },
  {
    "incidentId": "121761875",
    "incidentType": "PO",
    "FACJobStatusCode": "D",
    "OANNumber": "1001329",
    "outageStartDateTime": "9/10/2019 8:00:00 AM",
    "versionDate": "9/10/2019 5:40:18 PM",
    "lastChangeDateTime": "9/10/2019 4:01:22 PM",
    "estimateCLUDateTime": "9/10/2019 7:00:00 PM",
    "memoCauseCode": "21",
    "memoCauseCodeDescription": "Pole Upgrade",
    "crewStatusCode": "04",
    "crewStatusCodeDescription": "Work is in progress.",
    "resultCode": "01",
    "resultCodeDesription": "Enhancing Reliability",
    "numberOfCustomersAffected": "1",
    "zipCode": "No Zip Code",
    "countyName": "San Bernardino                          ",
    "cityName": "Crestline",
    "districtNumber": "40",
    "sectorNumber": "ARROWHEAD",
    "ERTCode": "06",
    "centroidX": "-117.279519",
    "centroidY": "34.25417050000350"
  },
  {
    "incidentId": "121808746",
    "incidentType": "Not Available",
    "FACJobStatusCode": "W",
    "OANNumber": "1005125",
    "outageStartDateTime": "9/10/2019 8:00:00 AM",
    "versionDate": "9/10/2019 5:40:18 PM",
    "lastChangeDateTime": "9/10/2019 5:32:29 PM",
    "estimateCLUDateTime": "Currently Being Re-evaluated",
    "memoCauseCode": "07",
    "memoCauseCodeDescription": "Upgrading Equipment",
    "crewStatusCode": "04",
    "crewStatusCodeDescription": "Work is in progress.",
    "resultCode": "01",
    "resultCodeDesription": "Enhancing Reliability",
    "numberOfCustomersAffected": "58",
    "zipCode": "90250",
    "countyName": "Los Angeles                             ",
    "cityName": "Hawthorne",
    "districtNumber": "44",
    "sectorNumber": "EL NIDO",
    "ERTCode": "06",
    "centroidX": "-118.33170150",
    "centroidY": "33.90546700000350"
  },
  {
    "incidentId": "121807885",
    "incidentType": "Not Available",
    "FACJobStatusCode": "F",
    "OANNumber": "1004981",
    "outageStartDateTime": "9/10/2019 11:33:21 AM",
    "versionDate": "9/10/2019 5:40:18 PM",
    "lastChangeDateTime": "9/10/2019 5:33:53 PM",
    "estimateCLUDateTime": "9/10/2019 8:30:00 PM",
    "memoCauseCode": "11",
    "memoCauseCodeDescription": "Traffic Accident",
    "crewStatusCode": "04",
    "crewStatusCodeDescription": "Work is in progress.",
    "resultCode": "06",
    "resultCodeDesription": "Equipment Damage",
    "numberOfCustomersAffected": "9",
    "zipCode": "92866",
    "countyName": "Orange                                  ",
    "cityName": "Orange",
    "districtNumber": "29",
    "sectorNumber": "VILLA PARK",
    "ERTCode": "07",
    "centroidX": "-117.847110749775",
    "centroidY": "33.78847550012690"
  },
  {
    "incidentId": "121808168",
    "incidentType": "Not Available",
    "FACJobStatusCode": "D",
    "OANNumber": "1005119",
    "outageStartDateTime": "9/10/2019 1:15:24 PM",
    "versionDate": "9/10/2019 5:40:18 PM",
    "lastChangeDateTime": "9/10/2019 4:38:42 PM",
    "estimateCLUDateTime": "Most up by 9/10/2019 11:00:00 PM",
    "memoCauseCode": "15",
    "memoCauseCodeDescription": "Analyzing Problem",
    "crewStatusCode": "01",
    "crewStatusCodeDescription": "We are aware of the problem.",
    "resultCode": "0",
    "resultCodeDesription": "Not Available",
    "numberOfCustomersAffected": "6",
    "zipCode": "90715",
    "countyName": "Los Angeles                             ",
    "cityName": "Lakewood",
    "districtNumber": "46",
    "sectorNumber": "LIGHTHIPE",
    "ERTCode": "05",
    "centroidX": "-118.06007950",
    "centroidY": "33.83713700000640"
  },
  {
    "incidentId": "121764984",
    "incidentType": "PO",
    "FACJobStatusCode": "D",
    "OANNumber": "1001790",
    "outageStartDateTime": "9/10/2019 8:10:07 AM",
    "versionDate": "9/10/2019 5:40:18 PM",
    "lastChangeDateTime": "9/10/2019 3:59:15 PM",
    "estimateCLUDateTime": "9/10/2019 8:00:00 PM",
    "memoCauseCode": "07",
    "memoCauseCodeDescription": "Upgrading Equipment",
    "crewStatusCode": "04",
    "crewStatusCodeDescription": "Work is in progress.",
    "resultCode": "01",
    "resultCodeDesription": "Enhancing Reliability",
    "numberOfCustomersAffected": "2",
    "zipCode": "93040",
    "countyName": "Ventura                                 ",
    "cityName": "Unincorporated Area - Ventura County",
    "districtNumber": "59",
    "sectorNumber": "SAUGUS",
    "ERTCode": "07",
    "centroidX": "-118.719772500079",
    "centroidY": "34.384512252671"
  },
  {
    "incidentId": "121808741",
    "incidentType": "QI",
    "FACJobStatusCode": "D",
    "OANNumber": "1005124",
    "outageStartDateTime": "9/10/2019 4:48:29 PM",
    "versionDate": "9/10/2019 5:40:18 PM",
    "lastChangeDateTime": "9/10/2019 5:04:57 PM",
    "estimateCLUDateTime": "9/10/2019 7:00:00 PM",
    "memoCauseCode": "16",
    "memoCauseCodeDescription": "Equipment Problems",
    "crewStatusCode": "04",
    "crewStatusCodeDescription": "Work is in progress.",
    "resultCode": "0",
    "resultCodeDesription": "Not Available",
    "numberOfCustomersAffected": "7",
    "zipCode": "91320",
    "countyName": "Ventura                                 ",
    "cityName": "Unincorporated Area - Ventura County",
    "districtNumber": "35",
    "sectorNumber": "MOORPARK",
    "ERTCode": "06",
    "centroidX": "-118.90607450",
    "centroidY": "34.16936100000350"
  },
  {
    "incidentId": "121763486",
    "incidentType": "PO",
    "FACJobStatusCode": "F",
    "OANNumber": "1001589",
    "outageStartDateTime": "9/10/2019 9:25:00 AM",
    "versionDate": "9/10/2019 5:40:18 PM",
    "lastChangeDateTime": "9/10/2019 5:36:36 PM",
    "estimateCLUDateTime": "9/10/2019 8:00:00 PM",
    "memoCauseCode": "21",
    "memoCauseCodeDescription": "Pole Upgrade",
    "crewStatusCode": "04",
    "crewStatusCodeDescription": "Work is in progress.",
    "resultCode": "01",
    "resultCodeDesription": "Enhancing Reliability",
    "numberOfCustomersAffected": "27",
    "zipCode": "90650",
    "countyName": "Los Angeles                             ",
    "cityName": "Norwalk",
    "districtNumber": "47",
    "sectorNumber": "LIGHTHIPE",
    "ERTCode": "07",
    "centroidX": "-118.073749749959",
    "centroidY": "33.91611325075640"
  },
  {
    "incidentId": "121808448",
    "incidentType": "Not Available",
    "FACJobStatusCode": "D",
    "OANNumber": "1005083",
    "outageStartDateTime": "9/9/2019 10:23:21 AM",
    "versionDate": "9/10/2019 5:40:18 PM",
    "lastChangeDateTime": "9/10/2019 4:24:43 PM",
    "estimateCLUDateTime": "Most up by 9/10/2019 11:00:00 PM",
    "memoCauseCode": "15",
    "memoCauseCodeDescription": "Analyzing Problem",
    "crewStatusCode": "01",
    "crewStatusCodeDescription": "We are aware of the problem.",
    "resultCode": "0",
    "resultCodeDesription": "Not Available",
    "numberOfCustomersAffected": "26",
    "zipCode": "90266",
    "countyName": "Los Angeles                             ",
    "cityName": "Manhattan Beach",
    "districtNumber": "44",
    "sectorNumber": "EL NIDO",
    "ERTCode": "05",
    "centroidX": "-118.42008650",
    "centroidY": "33.90239600000350"
  },
  {
    "incidentId": "121766425",
    "incidentType": "PO",
    "FACJobStatusCode": "D",
    "OANNumber": "1001917",
    "outageStartDateTime": "9/10/2019 9:15:00 AM",
    "versionDate": "9/10/2019 5:40:18 PM",
    "lastChangeDateTime": "9/10/2019 4:01:00 PM",
    "estimateCLUDateTime": "9/10/2019 7:00:00 PM",
    "memoCauseCode": "21",
    "memoCauseCodeDescription": "Pole Upgrade",
    "crewStatusCode": "04",
    "crewStatusCodeDescription": "Work is in progress.",
    "resultCode": "01",
    "resultCodeDesription": "Enhancing Reliability",
    "numberOfCustomersAffected": "152",
    "zipCode": "No Zip Code",
    "countyName": "San Bernardino                          ",
    "cityName": "Crestline",
    "districtNumber": "40",
    "sectorNumber": "ARROWHEAD",
    "ERTCode": "06",
    "centroidX": "-117.280038638475",
    "centroidY": "34.24957229829590"
  },
  {
    "incidentId": "121760838",
    "incidentType": "PO",
    "FACJobStatusCode": "D",
    "OANNumber": "1001159",
    "outageStartDateTime": "9/10/2019 8:03:00 AM",
    "versionDate": "9/10/2019 5:40:18 PM",
    "lastChangeDateTime": "9/10/2019 4:40:49 PM",
    "estimateCLUDateTime": "9/10/2019 6:30:00 PM",
    "memoCauseCode": "07",
    "memoCauseCodeDescription": "Upgrading Equipment",
    "crewStatusCode": "04",
    "crewStatusCodeDescription": "Work is in progress.",
    "resultCode": "01",
    "resultCodeDesription": "Enhancing Reliability",
    "numberOfCustomersAffected": "25",
    "zipCode": "93285",
    "countyName": "Kern                                    ",
    "cityName": "Wofford Heights",
    "districtNumber": "53",
    "sectorNumber": "KERNVILLE",
    "ERTCode": "07",
    "centroidX": "-118.453324331606",
    "centroidY": "35.70742650037240"
  },
  {
    "incidentId": "121762197",
    "incidentType": "PO",
    "FACJobStatusCode": "D",
    "OANNumber": "1001392",
    "outageStartDateTime": "9/10/2019 9:00:00 AM",
    "versionDate": "9/10/2019 5:40:18 PM",
    "lastChangeDateTime": "9/10/2019 3:29:27 PM",
    "estimateCLUDateTime": "9/10/2019 8:00:00 PM",
    "memoCauseCode": "21",
    "memoCauseCodeDescription": "Pole Upgrade",
    "crewStatusCode": "04",
    "crewStatusCodeDescription": "Work is in progress.",
    "resultCode": "01",
    "resultCodeDesription": "Enhancing Reliability",
    "numberOfCustomersAffected": "25",
    "zipCode": "No Zip Code",
    "countyName": "San Bernardino                          ",
    "cityName": "Lake Arrowhead",
    "districtNumber": "40",
    "sectorNumber": "ARROWHEAD",
    "ERTCode": "07",
    "centroidX": "-117.200019248579",
    "centroidY": "34.26802200044630"
  },
  {
    "incidentId": "121762224",
    "incidentType": "PO",
    "FACJobStatusCode": "W",
    "OANNumber": "1001399",
    "outageStartDateTime": "9/10/2019 9:15:00 AM",
    "versionDate": "9/10/2019 5:40:18 PM",
    "lastChangeDateTime": "9/10/2019 3:51:47 PM",
    "estimateCLUDateTime": "9/10/2019 7:00:00 PM",
    "memoCauseCode": "21",
    "memoCauseCodeDescription": "Pole Upgrade",
    "crewStatusCode": "04",
    "crewStatusCodeDescription": "Work is in progress.",
    "resultCode": "01",
    "resultCodeDesription": "Enhancing Reliability",
    "numberOfCustomersAffected": "10",
    "zipCode": "No Zip Code",
    "countyName": "San Bernardino                          ",
    "cityName": "Crestline",
    "districtNumber": "40",
    "sectorNumber": "ARROWHEAD",
    "ERTCode": "07",
    "centroidX": "-117.280215812196",
    "centroidY": "34.24934871660820"
  },
  {
    "incidentId": "121767095",
    "incidentType": "PO",
    "FACJobStatusCode": "W",
    "OANNumber": "1002044",
    "outageStartDateTime": "9/10/2019 9:00:00 AM",
    "versionDate": "9/10/2019 5:40:18 PM",
    "lastChangeDateTime": "9/10/2019 5:30:42 PM",
    "estimateCLUDateTime": "Currently Being Re-evaluated",
    "memoCauseCode": "21",
    "memoCauseCodeDescription": "Pole Upgrade",
    "crewStatusCode": "04",
    "crewStatusCodeDescription": "Work is in progress.",
    "resultCode": "01",
    "resultCodeDesription": "Enhancing Reliability",
    "numberOfCustomersAffected": "279",
    "zipCode": "92595",
    "countyName": "Riverside                               ",
    "cityName": "Wildomar",
    "districtNumber": "88",
    "sectorNumber": "VALLEY",
    "ERTCode": "07",
    "centroidX": "-117.280839616051",
    "centroidY": "33.64291959826310"
  },
  {
    "incidentId": "121808054",
    "incidentType": "Not Available",
    "FACJobStatusCode": "D",
    "OANNumber": "1005011",
    "outageStartDateTime": "9/10/2019 12:32:35 PM",
    "versionDate": "9/10/2019 5:40:18 PM",
    "lastChangeDateTime": "9/10/2019 5:02:53 PM",
    "estimateCLUDateTime": "9/11/2019 12:00:00 AM",
    "memoCauseCode": "16",
    "memoCauseCodeDescription": "Equipment Problems",
    "crewStatusCode": "03",
    "crewStatusCodeDescription": "Our crews are on the way. ",
    "resultCode": "0",
    "resultCodeDesription": "Not Available",
    "numberOfCustomersAffected": "51",
    "zipCode": "92870",
    "countyName": "Orange                                  ",
    "cityName": "Placentia",
    "districtNumber": "48",
    "sectorNumber": "VILLA PARK",
    "ERTCode": "06",
    "centroidX": "-117.820606900459",
    "centroidY": "33.87112600084710"
  },
  {
    "incidentId": "121808763",
    "incidentType": "QI",
    "FACJobStatusCode": "U",
    "OANNumber": "1005126",
    "outageStartDateTime": "9/10/2019 5:21:29 PM",
    "versionDate": "9/10/2019 5:40:18 PM",
    "lastChangeDateTime": "9/10/2019 5:22:43 PM",
    "estimateCLUDateTime": "9/11/2019 10:00:00 PM",
    "memoCauseCode": "16",
    "memoCauseCodeDescription": "Equipment Problems",
    "crewStatusCode": "04",
    "crewStatusCodeDescription": "Work is in progress.",
    "resultCode": "0",
    "resultCodeDesription": "Not Available",
    "numberOfCustomersAffected": "5",
    "zipCode": "90621",
    "countyName": "Orange                                  ",
    "cityName": "Buena Park",
    "districtNumber": "48",
    "sectorNumber": "VILLA PARK",
    "ERTCode": "06",
    "centroidX": "-117.99922550",
    "centroidY": "33.87788400000740"
  },
  {
    "incidentId": "121762683",
    "incidentType": "PO",
    "FACJobStatusCode": "D",
    "OANNumber": "1001491",
    "outageStartDateTime": "9/10/2019 8:00:59 AM",
    "versionDate": "9/10/2019 5:40:18 PM",
    "lastChangeDateTime": "9/10/2019 4:06:03 PM",
    "estimateCLUDateTime": "9/10/2019 6:30:00 PM",
    "memoCauseCode": "23",
    "memoCauseCodeDescription": "Cable Upgrade",
    "crewStatusCode": "04",
    "crewStatusCodeDescription": "Work is in progress.",
    "resultCode": "01",
    "resultCodeDesription": "Enhancing Reliability",
    "numberOfCustomersAffected": "56",
    "zipCode": "93012",
    "countyName": "Ventura                                 ",
    "cityName": "Camarillo",
    "districtNumber": "39",
    "sectorNumber": "SANTA CLARA",
    "ERTCode": "07",
    "centroidX": "-118.987291102566",
    "centroidY": "34.21732850124580"
  },
  {
    "incidentId": "121762699",
    "incidentType": "PO",
    "FACJobStatusCode": "D",
    "OANNumber": "1001494",
    "outageStartDateTime": "9/10/2019 8:00:00 AM",
    "versionDate": "9/10/2019 5:40:18 PM",
    "lastChangeDateTime": "9/10/2019 11:26:03 AM",
    "estimateCLUDateTime": "9/10/2019 7:00:00 PM",
    "memoCauseCode": "21",
    "memoCauseCodeDescription": "Pole Upgrade",
    "crewStatusCode": "04",
    "crewStatusCodeDescription": "Work is in progress.",
    "resultCode": "01",
    "resultCodeDesription": "Enhancing Reliability",
    "numberOfCustomersAffected": "108",
    "zipCode": "91011",
    "countyName": "Los Angeles                             ",
    "cityName": "La Canada Flintridge",
    "districtNumber": "27",
    "sectorNumber": "MESA",
    "ERTCode": "07",
    "centroidX": "-118.176674427379",
    "centroidY": "34.20602308419690"
  }
]