[
  {
    "incidentId": "121764771",
    "incidentType": "PO",
    "FACJobStatusCode": "D",
    "OANNumber": "1001753",
    "outageStartDateTime": "9/9/2019 8:00:00 AM",
    "versionDate": "9/9/2019 5:54:08 PM",
    "lastChangeDateTime": "9/9/2019 5:47:35 PM",
    "estimateCLUDateTime": "9/9/2019 8:00:00 PM",
    "memoCauseCode": "21",
    "memoCauseCodeDescription": "Pole Upgrade",
    "crewStatusCode": "09",
    "crewStatusCodeDescription": "We have completed this repair.",
    "resultCode": "01",
    "resultCodeDesription": "Enhancing Reliability",
    "numberOfCustomersAffected": "8",
    "zipCode": "92325",
    "countyName": "San Bernardino                          ",
    "cityName": "Crestline",
    "districtNumber": "40",
    "sectorNumber": "ARROWHEAD",
    "ERTCode": "07",
    "centroidX": "-117.264684143536",
    "centroidY": "34.24551501274280"
  },
  {
    "incidentId": "121806172",
    "incidentType": "QI",
    "FACJobStatusCode": "U",
    "OANNumber": "1004854",
    "outageStartDateTime": "9/9/2019 5:16:10 PM",
    "versionDate": "9/9/2019 5:54:08 PM",
    "lastChangeDateTime": "9/9/2019 5:19:02 PM",
    "estimateCLUDateTime": "9/9/2019 9:00:00 PM",
    "memoCauseCode": "16",
    "memoCauseCodeDescription": "Equipment Problems",
    "crewStatusCode": "04",
    "crewStatusCodeDescription": "Work is in progress.",
    "resultCode": "0",
    "resultCodeDesription": "Not Available",
    "numberOfCustomersAffected": "17",
    "zipCode": "90803",
    "countyName": "Los Angeles                             ",
    "cityName": "Long Beach",
    "districtNumber": "46",
    "sectorNumber": "LIGHTHIPE",
    "ERTCode": "06",
    "centroidX": "-118.10838750",
    "centroidY": "33.77099300000360"
  },
  {
    "incidentId": "121806183",
    "incidentType": "QI",
    "FACJobStatusCode": "U",
    "OANNumber": "1004855",
    "outageStartDateTime": "9/9/2019 5:20:52 PM",
    "versionDate": "9/9/2019 5:54:08 PM",
    "lastChangeDateTime": "9/9/2019 5:23:24 PM",
    "estimateCLUDateTime": "9/9/2019 9:00:00 PM",
    "memoCauseCode": "16",
    "memoCauseCodeDescription": "Equipment Problems",
    "crewStatusCode": "04",
    "crewStatusCodeDescription": "Work is in progress.",
    "resultCode": "0",
    "resultCodeDesription": "Not Available",
    "numberOfCustomersAffected": "8",
    "zipCode": "92860",
    "countyName": "Riverside                               ",
    "cityName": "Norco",
    "districtNumber": "34",
    "sectorNumber": "MIRALOMA",
    "ERTCode": "06",
    "centroidX": "-117.552656",
    "centroidY": "33.91333900000370"
  },
  {
    "incidentId": "121750814",
    "incidentType": "PO",
    "FACJobStatusCode": "D",
    "OANNumber": "1000064",
    "outageStartDateTime": "9/9/2019 9:00:00 AM",
    "versionDate": "9/9/2019 5:54:08 PM",
    "lastChangeDateTime": "9/9/2019 3:40:44 PM",
    "estimateCLUDateTime": "9/9/2019 7:00:00 PM",
    "memoCauseCode": "21",
    "memoCauseCodeDescription": "Pole Upgrade",
    "crewStatusCode": "04",
    "crewStatusCodeDescription": "Work is in progress.",
    "resultCode": "01",
    "resultCodeDesription": "Enhancing Reliability",
    "numberOfCustomersAffected": "32",
    "zipCode": "91741",
    "countyName": "Los Angeles                             ",
    "cityName": "Glendora",
    "districtNumber": "26",
    "sectorNumber": "MIRALOMA",
    "ERTCode": "07",
    "centroidX": "-117.856232111651",
    "centroidY": "34.14870783470040"
  },
  {
    "incidentId": "121804417",
    "incidentType": "Not Available",
    "FACJobStatusCode": "D",
    "OANNumber": "1004599",
    "outageStartDateTime": "9/9/2019 8:14:38 AM",
    "versionDate": "9/9/2019 5:54:08 PM",
    "lastChangeDateTime": "9/9/2019 5:21:16 PM",
    "estimateCLUDateTime": "Currently Being Re-evaluated",
    "memoCauseCode": "16",
    "memoCauseCodeDescription": "Equipment Problems",
    "crewStatusCode": "04",
    "crewStatusCodeDescription": "Work is in progress.",
    "resultCode": "0",
    "resultCodeDesription": "Not Available",
    "numberOfCustomersAffected": "4",
    "zipCode": "No Zip Code",
    "countyName": "San Bernardino                          ",
    "cityName": "Unincorporated Area - San Bernardino County",
    "districtNumber": "40",
    "sectorNumber": "ARROWHEAD",
    "ERTCode": "06",
    "centroidX": "-117.148741006534",
    "centroidY": "34.23514075440130"
  },
  {
    "incidentId": "121761916",
    "incidentType": "PO",
    "FACJobStatusCode": "D",
    "OANNumber": "1001337",
    "outageStartDateTime": "9/9/2019 8:05:02 AM",
    "versionDate": "9/9/2019 5:54:08 PM",
    "lastChangeDateTime": "9/9/2019 5:41:30 PM",
    "estimateCLUDateTime": "Currently Being Re-evaluated",
    "memoCauseCode": "21",
    "memoCauseCodeDescription": "Pole Upgrade",
    "crewStatusCode": "04",
    "crewStatusCodeDescription": "Work is in progress.",
    "resultCode": "01",
    "resultCodeDesription": "Enhancing Reliability",
    "numberOfCustomersAffected": "13",
    "zipCode": "93023",
    "countyName": "Ventura                                 ",
    "cityName": "Unincorporated Area - Ventura County",
    "districtNumber": "39",
    "sectorNumber": "SANTA CLARA",
    "ERTCode": "06",
    "centroidX": "-119.203994620351",
    "centroidY": "34.44384762667070"
  },
  {
    "incidentId": "121804725",
    "incidentType": "QI",
    "FACJobStatusCode": "D",
    "OANNumber": "1004634",
    "outageStartDateTime": "9/9/2019 9:21:07 AM",
    "versionDate": "9/9/2019 5:54:08 PM",
    "lastChangeDateTime": "9/9/2019 4:10:56 PM",
    "estimateCLUDateTime": "Currently Being Re-evaluated",
    "memoCauseCode": "16",
    "memoCauseCodeDescription": "Equipment Problems",
    "crewStatusCode": "04",
    "crewStatusCodeDescription": "Work is in progress.",
    "resultCode": "0",
    "resultCodeDesription": "Not Available",
    "numberOfCustomersAffected": "29",
    "zipCode": "90631",
    "countyName": "Orange                                  ",
    "cityName": "La Habra",
    "districtNumber": "48",
    "sectorNumber": "VILLA PARK",
    "ERTCode": "07",
    "centroidX": "-117.95556750",
    "centroidY": "33.92058900000640"
  },
  {
    "incidentId": "121804970",
    "incidentType": "Not Available",
    "FACJobStatusCode": "A",
    "OANNumber": "1004686",
    "outageStartDateTime": "9/9/2019 10:12:01 AM",
    "versionDate": "9/9/2019 5:54:08 PM",
    "lastChangeDateTime": "9/9/2019 4:22:23 PM",
    "estimateCLUDateTime": "Most up by 9/9/2019 10:00:00 PM",
    "memoCauseCode": "16",
    "memoCauseCodeDescription": "Equipment Problems",
    "crewStatusCode": "11",
    "crewStatusCodeDescription": "We have identified the problem and are working to restore your service.",
    "resultCode": "0",
    "resultCodeDesription": "Not Available",
    "numberOfCustomersAffected": "7",
    "zipCode": "92504",
    "countyName": "Riverside                               ",
    "cityName": "Unincorporated Area - Riverside County",
    "districtNumber": "77",
    "sectorNumber": "VALLEY",
    "ERTCode": "05",
    "centroidX": "-117.37307450",
    "centroidY": "33.88155200000640"
  },
  {
    "incidentId": "121805156",
    "incidentType": "Not Available",
    "FACJobStatusCode": "A",
    "OANNumber": "1004710",
    "outageStartDateTime": "9/9/2019 10:57:15 AM",
    "versionDate": "9/9/2019 5:54:08 PM",
    "lastChangeDateTime": "9/9/2019 2:26:24 PM",
    "estimateCLUDateTime": "Currently Being Re-evaluated",
    "memoCauseCode": "11",
    "memoCauseCodeDescription": "Traffic Accident",
    "crewStatusCode": "11",
    "crewStatusCodeDescription": "We have identified the problem and are working to restore your service.",
    "resultCode": "02",
    "resultCodeDesription": "Power Poles and Lines Down",
    "numberOfCustomersAffected": "15",
    "zipCode": "92780",
    "countyName": "Orange                                  ",
    "cityName": "Tustin",
    "districtNumber": "29",
    "sectorNumber": "VILLA PARK",
    "ERTCode": "05",
    "centroidX": "-117.82898150",
    "centroidY": "33.75995950000340"
  },
  {
    "incidentId": "121805533",
    "incidentType": "Not Available",
    "FACJobStatusCode": "D",
    "OANNumber": "1004758",
    "outageStartDateTime": "9/9/2019 12:56:27 PM",
    "versionDate": "9/9/2019 5:54:08 PM",
    "lastChangeDateTime": "9/9/2019 4:48:35 PM",
    "estimateCLUDateTime": "9/9/2019 10:00:00 PM",
    "memoCauseCode": "16",
    "memoCauseCodeDescription": "Equipment Problems",
    "crewStatusCode": "04",
    "crewStatusCodeDescription": "Work is in progress.",
    "resultCode": "0",
    "resultCodeDesription": "Not Available",
    "numberOfCustomersAffected": "3",
    "zipCode": "90248",
    "countyName": "Los Angeles                             ",
    "cityName": "Gardena",
    "districtNumber": "44",
    "sectorNumber": "EL NIDO",
    "ERTCode": "07",
    "centroidX": "-118.30250450",
    "centroidY": "33.86835800000350"
  },
  {
    "incidentId": "121805534",
    "incidentType": "Not Available",
    "FACJobStatusCode": "D",
    "OANNumber": "1004759",
    "outageStartDateTime": "9/9/2019 12:56:27 PM",
    "versionDate": "9/9/2019 5:54:08 PM",
    "lastChangeDateTime": "9/9/2019 4:49:14 PM",
    "estimateCLUDateTime": "9/9/2019 10:00:00 PM",
    "memoCauseCode": "16",
    "memoCauseCodeDescription": "Equipment Problems",
    "crewStatusCode": "04",
    "crewStatusCodeDescription": "Work is in progress.",
    "resultCode": "0",
    "resultCodeDesription": "Not Available",
    "numberOfCustomersAffected": "2",
    "zipCode": "90248",
    "countyName": "Los Angeles                             ",
    "cityName": "Gardena",
    "districtNumber": "44",
    "sectorNumber": "EL NIDO",
    "ERTCode": "07",
    "centroidX": "-118.30251050",
    "centroidY": "33.86871900000350"
  },
  {
    "incidentId": "121761802",
    "incidentType": "PO",
    "FACJobStatusCode": "D",
    "OANNumber": "1001312",
    "outageStartDateTime": "9/9/2019 9:00:00 AM",
    "versionDate": "9/9/2019 5:54:08 PM",
    "lastChangeDateTime": "9/9/2019 4:28:27 PM",
    "estimateCLUDateTime": "9/9/2019 9:00:00 PM",
    "memoCauseCode": "21",
    "memoCauseCodeDescription": "Pole Upgrade",
    "crewStatusCode": "04",
    "crewStatusCodeDescription": "Work is in progress.",
    "resultCode": "01",
    "resultCodeDesription": "Enhancing Reliability",
    "numberOfCustomersAffected": "17",
    "zipCode": "91006",
    "countyName": "Los Angeles                             ",
    "cityName": "Arcadia",
    "districtNumber": "27",
    "sectorNumber": "MESA",
    "ERTCode": "07",
    "centroidX": "-118.023401125519",
    "centroidY": "34.17677050143610"
  },
  {
    "incidentId": "121765045",
    "incidentType": "PO",
    "FACJobStatusCode": "F",
    "OANNumber": "1001801",
    "outageStartDateTime": "9/9/2019 9:00:00 AM",
    "versionDate": "9/9/2019 5:54:08 PM",
    "lastChangeDateTime": "9/9/2019 5:48:08 PM",
    "estimateCLUDateTime": "Most up by 9/9/2019 7:30:00 PM",
    "memoCauseCode": "07",
    "memoCauseCodeDescription": "Upgrading Equipment",
    "crewStatusCode": "04",
    "crewStatusCodeDescription": "Work is in progress.",
    "resultCode": "01",
    "resultCodeDesription": "Enhancing Reliability",
    "numberOfCustomersAffected": "4",
    "zipCode": "91387",
    "countyName": "Los Angeles                             ",
    "cityName": "Santa Clarita",
    "districtNumber": "59",
    "sectorNumber": "SAUGUS",
    "ERTCode": "09",
    "centroidX": "-118.446106739550",
    "centroidY": "34.41178549317310"
  },
  {
    "incidentId": "121805229",
    "incidentType": "Not Available",
    "FACJobStatusCode": "D",
    "OANNumber": "1004853",
    "outageStartDateTime": "9/9/2019 11:18:15 AM",
    "versionDate": "9/9/2019 5:54:08 PM",
    "lastChangeDateTime": "9/9/2019 5:30:03 PM",
    "estimateCLUDateTime": "Most up by 9/9/2019 7:00:00 PM",
    "memoCauseCode": "15",
    "memoCauseCodeDescription": "Analyzing Problem",
    "crewStatusCode": "09",
    "crewStatusCodeDescription": "We have completed this repair.",
    "resultCode": "0",
    "resultCodeDesription": "Not Available",
    "numberOfCustomersAffected": "18",
    "zipCode": "91001",
    "countyName": "Los Angeles                             ",
    "cityName": "Unincorporated Area - Los Angeles County",
    "districtNumber": "27",
    "sectorNumber": "MESA",
    "ERTCode": "05",
    "centroidX": "-118.12935250",
    "centroidY": "34.18151250000340"
  },
  {
    "incidentId": "121761822",
    "incidentType": "PO",
    "FACJobStatusCode": "D",
    "OANNumber": "1001316",
    "outageStartDateTime": "9/9/2019 8:09:18 AM",
    "versionDate": "9/9/2019 5:54:08 PM",
    "lastChangeDateTime": "9/9/2019 4:48:34 PM",
    "estimateCLUDateTime": "Currently Being Re-evaluated",
    "memoCauseCode": "07",
    "memoCauseCodeDescription": "Upgrading Equipment",
    "crewStatusCode": "04",
    "crewStatusCodeDescription": "Work is in progress.",
    "resultCode": "01",
    "resultCodeDesription": "Enhancing Reliability",
    "numberOfCustomersAffected": "55",
    "zipCode": "93561",
    "countyName": "Kern                                    ",
    "cityName": "Bear Valley Springs",
    "districtNumber": "52",
    "sectorNumber": "TEHACHAPI",
    "ERTCode": "06",
    "centroidX": "-118.654560477354",
    "centroidY": "35.17441847961850"
  },
  {
    "incidentId": "121711587",
    "incidentType": "PO",
    "FACJobStatusCode": "D",
    "OANNumber": "995924",
    "outageStartDateTime": "9/9/2019 12:38:25 PM",
    "versionDate": "9/9/2019 5:54:08 PM",
    "lastChangeDateTime": "9/9/2019 5:26:41 PM",
    "estimateCLUDateTime": "9/9/2019 7:00:00 PM",
    "memoCauseCode": "21",
    "memoCauseCodeDescription": "Pole Upgrade",
    "crewStatusCode": "04",
    "crewStatusCodeDescription": "Work is in progress.",
    "resultCode": "01",
    "resultCodeDesription": "Enhancing Reliability",
    "numberOfCustomersAffected": "2",
    "zipCode": "93023",
    "countyName": "Ventura                                 ",
    "cityName": "Unincorporated Area - Ventura County",
    "districtNumber": "39",
    "sectorNumber": "SANTA CLARA",
    "ERTCode": "06",
    "centroidX": "-119.270415515045",
    "centroidY": "34.41162225532620"
  },
  {
    "incidentId": "121761424",
    "incidentType": "PO",
    "FACJobStatusCode": "D",
    "OANNumber": "1001237",
    "outageStartDateTime": "9/9/2019 8:00:00 AM",
    "versionDate": "9/9/2019 5:54:08 PM",
    "lastChangeDateTime": "9/9/2019 4:18:30 PM",
    "estimateCLUDateTime": "Currently Being Re-evaluated",
    "memoCauseCode": "18",
    "memoCauseCodeDescription": "Trees in Equipment",
    "crewStatusCode": "04",
    "crewStatusCodeDescription": "Work is in progress.",
    "resultCode": "01",
    "resultCodeDesription": "Enhancing Reliability",
    "numberOfCustomersAffected": "26",
    "zipCode": "No Zip Code",
    "countyName": "San Bernardino                          ",
    "cityName": "Crestline",
    "districtNumber": "40",
    "sectorNumber": "ARROWHEAD",
    "ERTCode": "07",
    "centroidX": "-117.275319624656",
    "centroidY": "34.24440975391290"
  },
  {
    "incidentId": "121761786",
    "incidentType": "PO",
    "FACJobStatusCode": "D",
    "OANNumber": "1001310",
    "outageStartDateTime": "9/9/2019 7:04:26 AM",
    "versionDate": "9/9/2019 5:54:08 PM",
    "lastChangeDateTime": "9/9/2019 2:46:25 PM",
    "estimateCLUDateTime": "9/9/2019 6:30:00 PM",
    "memoCauseCode": "07",
    "memoCauseCodeDescription": "Upgrading Equipment",
    "crewStatusCode": "04",
    "crewStatusCodeDescription": "Work is in progress.",
    "resultCode": "01",
    "resultCodeDesription": "Enhancing Reliability",
    "numberOfCustomersAffected": "126",
    "zipCode": "93040",
    "countyName": "Ventura                                 ",
    "cityName": "Piru",
    "districtNumber": "59",
    "sectorNumber": "SAUGUS",
    "ERTCode": "07",
    "centroidX": "-118.800488008615",
    "centroidY": "34.41474627735250"
  },
  {
    "incidentId": "121762767",
    "incidentType": "PO",
    "FACJobStatusCode": "W",
    "OANNumber": "1001509",
    "outageStartDateTime": "9/9/2019 9:00:00 AM",
    "versionDate": "9/9/2019 5:54:08 PM",
    "lastChangeDateTime": "9/9/2019 9:05:35 AM",
    "estimateCLUDateTime": "Currently Being Re-evaluated",
    "memoCauseCode": "21",
    "memoCauseCodeDescription": "Pole Upgrade",
    "crewStatusCode": "04",
    "crewStatusCodeDescription": "Work is in progress.",
    "resultCode": "01",
    "resultCodeDesription": "Enhancing Reliability",
    "numberOfCustomersAffected": "16",
    "zipCode": "92316",
    "countyName": "San Bernardino                          ",
    "cityName": "Unincorporated Area - San Bernardino County",
    "districtNumber": "30",
    "sectorNumber": "VISTA",
    "ERTCode": "07",
    "centroidX": "-117.393648333405",
    "centroidY": "34.04506683541320"
  },
  {
    "incidentId": "121765066",
    "incidentType": "PO",
    "FACJobStatusCode": "W",
    "OANNumber": "1001806",
    "outageStartDateTime": "9/9/2019 9:00:00 AM",
    "versionDate": "9/9/2019 5:54:08 PM",
    "lastChangeDateTime": "9/9/2019 3:27:30 PM",
    "estimateCLUDateTime": "9/9/2019 7:00:00 PM",
    "memoCauseCode": "21",
    "memoCauseCodeDescription": "Pole Upgrade",
    "crewStatusCode": "04",
    "crewStatusCodeDescription": "Work is in progress.",
    "resultCode": "01",
    "resultCodeDesription": "Enhancing Reliability",
    "numberOfCustomersAffected": "111",
    "zipCode": "92262",
    "countyName": "Riverside                               ",
    "cityName": "Palm Springs",
    "districtNumber": "79",
    "sectorNumber": "DEVERS",
    "ERTCode": "07",
    "centroidX": "-116.548773864607",
    "centroidY": "33.83272010266590"
  },
  {
    "incidentId": "121805016",
    "incidentType": "Not Available",
    "FACJobStatusCode": "F",
    "OANNumber": "1004674",
    "outageStartDateTime": "9/9/2019 10:08:44 AM",
    "versionDate": "9/9/2019 5:54:08 PM",
    "lastChangeDateTime": "9/9/2019 5:32:10 PM",
    "estimateCLUDateTime": "9/9/2019 7:00:00 PM",
    "memoCauseCode": "11",
    "memoCauseCodeDescription": "Traffic Accident",
    "crewStatusCode": "04",
    "crewStatusCodeDescription": "Work is in progress.",
    "resultCode": "06",
    "resultCodeDesription": "Equipment Damage",
    "numberOfCustomersAffected": "63",
    "zipCode": "92571",
    "countyName": "Riverside                               ",
    "cityName": "Perris",
    "districtNumber": "77",
    "sectorNumber": "VALLEY",
    "ERTCode": "06",
    "centroidX": "-117.221083911683",
    "centroidY": "33.79335391754150"
  },
  {
    "incidentId": "121804307",
    "incidentType": "Not Available",
    "FACJobStatusCode": "U",
    "OANNumber": "1004588",
    "outageStartDateTime": "9/9/2019 6:57:39 AM",
    "versionDate": "9/9/2019 5:54:08 PM",
    "lastChangeDateTime": "9/9/2019 6:58:34 AM",
    "estimateCLUDateTime": "Currently Being Re-evaluated",
    "memoCauseCode": "15",
    "memoCauseCodeDescription": "Analyzing Problem",
    "crewStatusCode": "02",
    "crewStatusCodeDescription": "We have notified our repair crews. ",
    "resultCode": "0",
    "resultCodeDesription": "Not Available",
    "numberOfCustomersAffected": "141",
    "zipCode": "No Zip Code",
    "countyName": "Los Angeles                             ",
    "cityName": "Unincorporated Area - Los Angeles County",
    "districtNumber": "61",
    "sectorNumber": "CATALINA",
    "ERTCode": "01",
    "centroidX": "-118.460221573238",
    "centroidY": "33.42653167887870"
  },
  {
    "incidentId": "121805432",
    "incidentType": "QI",
    "FACJobStatusCode": "D",
    "OANNumber": "1004731",
    "outageStartDateTime": "9/9/2019 9:57:29 AM",
    "versionDate": "9/9/2019 5:54:08 PM",
    "lastChangeDateTime": "9/9/2019 4:10:03 PM",
    "estimateCLUDateTime": "9/9/2019 9:00:00 PM",
    "memoCauseCode": "16",
    "memoCauseCodeDescription": "Equipment Problems",
    "crewStatusCode": "04",
    "crewStatusCodeDescription": "Work is in progress.",
    "resultCode": "0",
    "resultCodeDesription": "Not Available",
    "numberOfCustomersAffected": "13",
    "zipCode": "No Zip Code",
    "countyName": "San Bernardino                          ",
    "cityName": "Lake Arrowhead",
    "districtNumber": "40",
    "sectorNumber": "ARROWHEAD",
    "ERTCode": "07",
    "centroidX": "-117.179843",
    "centroidY": "34.24496900000370"
  },
  {
    "incidentId": "121806117",
    "incidentType": "Not Available",
    "FACJobStatusCode": "D",
    "OANNumber": "1004851",
    "outageStartDateTime": "9/9/2019 4:31:54 PM",
    "versionDate": "9/9/2019 5:54:08 PM",
    "lastChangeDateTime": "9/9/2019 4:53:22 PM",
    "estimateCLUDateTime": "9/9/2019 8:00:00 PM",
    "memoCauseCode": "16",
    "memoCauseCodeDescription": "Equipment Problems",
    "crewStatusCode": "02",
    "crewStatusCodeDescription": "We have notified our repair crews. ",
    "resultCode": "0",
    "resultCodeDesription": "Not Available",
    "numberOfCustomersAffected": "78",
    "zipCode": "90210",
    "countyName": "Los Angeles                             ",
    "cityName": "Beverly Hills",
    "districtNumber": "42",
    "sectorNumber": "EL NIDO",
    "ERTCode": "06",
    "centroidX": "-118.394518266250",
    "centroidY": "34.08290877908980"
  },
  {
    "incidentId": "121761579",
    "incidentType": "PO",
    "FACJobStatusCode": "W",
    "OANNumber": "1001261",
    "outageStartDateTime": "9/9/2019 9:30:00 AM",
    "versionDate": "9/9/2019 5:54:08 PM",
    "lastChangeDateTime": "9/9/2019 5:33:31 PM",
    "estimateCLUDateTime": "9/9/2019 6:30:00 PM",
    "memoCauseCode": "21",
    "memoCauseCodeDescription": "Pole Upgrade",
    "crewStatusCode": "04",
    "crewStatusCodeDescription": "Work is in progress.",
    "resultCode": "01",
    "resultCodeDesription": "Enhancing Reliability",
    "numberOfCustomersAffected": "11",
    "zipCode": "93001",
    "countyName": "Ventura                                 ",
    "cityName": "San Buenaventura (Ventura)",
    "districtNumber": "39",
    "sectorNumber": "SANTA CLARA",
    "ERTCode": "07",
    "centroidX": "-119.276845",
    "centroidY": "34.28757000000370"
  }
]